[
  {
    "ContainingType": "Project.Controllers.FarmerProductController",
    "Method": "GetProducts",
    "RelativePath": "api/FarmerProduct",
    "HttpMethod": "GET",
    "IsController": true,
    "Order": 0,
    "Parameters": [],
    "ReturnTypes": []
  },
  {
    "ContainingType": "Project.Controllers.FarmerProductController",
    "Method": "GetFarmerProductById",
    "RelativePath": "api/FarmerProduct/getById",
    "HttpMethod": "POST",
    "IsController": true,
    "Order": 0,
    "Parameters": [
      {
        "Name": "fptid",
        "Type": "System.Int32",
        "IsRequired": true
      }
    ],
    "ReturnTypes": []
  },
  {
    "ContainingType": "Project.Controllers.FarmerProductController",
    "Method": "GetProductTypes",
    "RelativePath": "api/FarmerProduct/GetProductTypes/{pid}",
    "HttpMethod": "GET",
    "IsController": true,
    "Order": 0,
    "Parameters": [
      {
        "Name": "pid",
        "Type": "System.Int32",
        "IsRequired": true
      }
    ],
    "ReturnTypes": []
  },
  {
    "ContainingType": "Project.Controllers.OrdersController",
    "Method": "GetOrders",
    "RelativePath": "api/Orders/GetOrders",
    "HttpMethod": "GET",
    "IsController": true,
    "Order": 0,
    "Parameters": [],
    "ReturnTypes": [
      {
        "Type": "System.Collections.Generic.List\u00601[[Project.Models.Order, Project, Version=1.0.0.0, Culture=neutral, PublicKeyToken=null]]",
        "MediaTypes": [
          "text/plain",
          "application/json",
          "text/json"
        ],
        "StatusCode": 200
      }
    ]
  },
  {
    "ContainingType": "Project.Controllers.OrdersController",
    "Method": "GetOrdersWithOrderDetails",
    "RelativePath": "api/Orders/GetOrdersWithOrderDetails",
    "HttpMethod": "GET",
    "IsController": true,
    "Order": 0,
    "Parameters": [],
    "ReturnTypes": [
      {
        "Type": "System.Collections.Generic.List\u00601[[Project.Models.Order, Project, Version=1.0.0.0, Culture=neutral, PublicKeyToken=null]]",
        "MediaTypes": [
          "text/plain",
          "application/json",
          "text/json"
        ],
        "StatusCode": 200
      }
    ]
  },
  {
    "ContainingType": "Project.Controllers.OrdersController",
    "Method": "SaveOrder",
    "RelativePath": "api/Orders/SaveOrder",
    "HttpMethod": "POST",
    "IsController": true,
    "Order": 0,
    "Parameters": [
      {
        "Name": "order",
        "Type": "Project.Models.Order",
        "IsRequired": true
      }
    ],
    "ReturnTypes": [
      {
        "Type": "Project.Models.Order",
        "MediaTypes": [
          "text/plain",
          "application/json",
          "text/json"
        ],
        "StatusCode": 200
      }
    ]
  },
  {
    "ContainingType": "Project.Controllers.PayemntController",
    "Method": "GetModes",
    "RelativePath": "api/Payemnt",
    "HttpMethod": "GET",
    "IsController": true,
    "Order": 0,
    "Parameters": [],
    "ReturnTypes": [
      {
        "Type": "System.Collections.Generic.List\u00601[[Project.Models.PaymentMode, Project, Version=1.0.0.0, Culture=neutral, PublicKeyToken=null]]",
        "MediaTypes": [
          "text/plain",
          "application/json",
          "text/json"
        ],
        "StatusCode": 200
      }
    ]
  },
  {
    "ContainingType": "Project.Controllers.PayemntController",
    "Method": "SaveMode",
    "RelativePath": "api/Payemnt",
    "HttpMethod": "POST",
    "IsController": true,
    "Order": 0,
    "Parameters": [
      {
        "Name": "mode",
        "Type": "Project.Models.PaymentMode",
        "IsRequired": true
      }
    ],
    "ReturnTypes": [
      {
        "Type": "Project.Models.PaymentMode",
        "MediaTypes": [
          "text/plain",
          "application/json",
          "text/json"
        ],
        "StatusCode": 200
      }
    ]
  }
]